{"persons":[{"id":1,"firstName":"Jairo","surName":"Johns","address":"8881 Wiegand Lock","avatar":"https://s3.amazonaws.com/uifaces/faces/twitter/darcystonge/128.jpg"},{"id":2,"firstName":"Jeramy","surName":"O'Hara","address":"6263 Otis Mission","avatar":"https://s3.amazonaws.com/uifaces/faces/twitter/doronmalki/128.jpg"},{"id":3,"firstName":"Lenore","surName":"Friesen","address":"421 Raleigh Forks","avatar":"https://s3.amazonaws.com/uifaces/faces/twitter/lisovsky/128.jpg"},{"id":4,"firstName":"Evie","surName":"Jacobs","address":"574 Lolita Crossroad","avatar":"https://s3.amazonaws.com/uifaces/faces/twitter/finchjke/128.jpg"},{"id":5,"firstName":"Prudence","surName":"Kshlerin","address":"33889 Sister Neck","avatar":"https://s3.amazonaws.com/uifaces/faces/twitter/nastya_mane/128.jpg"},{"id":6,"firstName":"Sheila","surName":"McDermott","address":"636 Rempel Ports","avatar":"https://s3.amazonaws.com/uifaces/faces/twitter/mylesb/128.jpg"},{"id":7,"firstName":"Abagail","surName":"Huel","address":"3504 Sporer Manors","avatar":"https://s3.amazonaws.com/uifaces/faces/twitter/aaronalfred/128.jpg"},{"id":8,"firstName":"Hollis","surName":"Bernhard","address":"30256 McCullough Avenue","avatar":"https://s3.amazonaws.com/uifaces/faces/twitter/mattlat/128.jpg"},{"id":9,"firstName":"Maybell","surName":"Stiedemann","address":"609 Dominic Dam","avatar":"https://s3.amazonaws.com/uifaces/faces/twitter/dcalonaci/128.jpg"},{"id":10,"firstName":"Aditya","surName":"Murphy","address":"8801 Huels Summit","avatar":"https://s3.amazonaws.com/uifaces/faces/twitter/sunlandictwin/128.jpg"},{"id":11,"firstName":"Jamie","surName":"Padberg","address":"96857 Casper Turnpike","avatar":"https://s3.amazonaws.com/uifaces/faces/twitter/allfordesign/128.jpg"},{"id":12,"firstName":"Carleton","surName":"Vandervort","address":"7485 Susan Springs","avatar":"https://s3.amazonaws.com/uifaces/faces/twitter/divya/128.jpg"},{"id":13,"firstName":"Lemuel","surName":"Mueller","address":"569 Merlin Cove","avatar":"https://s3.amazonaws.com/uifaces/faces/twitter/lebronjennan/128.jpg"},{"id":14,"firstName":"Saul","surName":"Wisoky","address":"766 Ansel Islands","avatar":"https://s3.amazonaws.com/uifaces/faces/twitter/anjhero/128.jpg"},{"id":15,"firstName":"Adah","surName":"Halvorson","address":"650 Kreiger Inlet","avatar":"https://s3.amazonaws.com/uifaces/faces/twitter/zforrester/128.jpg"},{"id":16,"firstName":"Danial","surName":"Botsford","address":"42714 Felipe Trail","avatar":"https://s3.amazonaws.com/uifaces/faces/twitter/ariffsetiawan/128.jpg"},{"id":17,"firstName":"Ottilie","surName":"Johnston","address":"7454 Romaguera Fields","avatar":"https://s3.amazonaws.com/uifaces/faces/twitter/gearpixels/128.jpg"},{"id":18,"firstName":"Ellsworth","surName":"Emmerich","address":"600 Brittany Extension","avatar":"https://s3.amazonaws.com/uifaces/faces/twitter/cdavis565/128.jpg"},{"id":19,"firstName":"Ciara","surName":"Legros","address":"76703 Hilll Inlet","avatar":"https://s3.amazonaws.com/uifaces/faces/twitter/andyisonline/128.jpg"},{"id":20,"firstName":"Dovie","surName":"Conroy","address":"27355 Wolf Heights","avatar":"https://s3.amazonaws.com/uifaces/faces/twitter/joshmedeski/128.jpg"},{"id":21,"firstName":"Leora","surName":"Wilkinson","address":"05709 Jovanny Village","avatar":"https://s3.amazonaws.com/uifaces/faces/twitter/bcrad/128.jpg"},{"id":22,"firstName":"Luz","surName":"Pfannerstill","address":"91591 Dale Springs","avatar":"https://s3.amazonaws.com/uifaces/faces/twitter/joaoedumedeiros/128.jpg"},{"id":23,"firstName":"Monserrat","surName":"Koss","address":"95506 Cary Estates","avatar":"https://s3.amazonaws.com/uifaces/faces/twitter/devinhalladay/128.jpg"},{"id":24,"firstName":"Osvaldo","surName":"Oberbrunner","address":"02323 Lang Vista","avatar":"https://s3.amazonaws.com/uifaces/faces/twitter/robergd/128.jpg"},{"id":25,"firstName":"Hosea","surName":"Wiegand","address":"267 Devan Port","avatar":"https://s3.amazonaws.com/uifaces/faces/twitter/webtanya/128.jpg"},{"id":26,"firstName":"Michelle","surName":"Glover","address":"334 Norbert View","avatar":"https://s3.amazonaws.com/uifaces/faces/twitter/algunsanabria/128.jpg"},{"id":27,"firstName":"Leola","surName":"Johnston","address":"447 Konopelski Course","avatar":"https://s3.amazonaws.com/uifaces/faces/twitter/nessoila/128.jpg"},{"id":28,"firstName":"Marian","surName":"Murray","address":"949 Stiedemann Lake","avatar":"https://s3.amazonaws.com/uifaces/faces/twitter/borges_marcos/128.jpg"},{"id":29,"firstName":"Timothy","surName":"Kris","address":"742 Stracke Manor","avatar":"https://s3.amazonaws.com/uifaces/faces/twitter/ma_tiax/128.jpg"},{"id":30,"firstName":"Mortimer","surName":"Anderson","address":"96380 Ruecker Valleys","avatar":"https://s3.amazonaws.com/uifaces/faces/twitter/plbabin/128.jpg"},{"id":31,"firstName":"Julian","surName":"Gaylord","address":"6427 Gleason Wall","avatar":"https://s3.amazonaws.com/uifaces/faces/twitter/haruintesettden/128.jpg"},{"id":32,"firstName":"Freda","surName":"Swift","address":"34978 Dante Court","avatar":"https://s3.amazonaws.com/uifaces/faces/twitter/chrisslowik/128.jpg"},{"id":33,"firstName":"Adrien","surName":"Becker","address":"46022 Ledner Villages","avatar":"https://s3.amazonaws.com/uifaces/faces/twitter/mikebeecham/128.jpg"},{"id":34,"firstName":"Jacynthe","surName":"Littel","address":"87512 Fritsch Ramp","avatar":"https://s3.amazonaws.com/uifaces/faces/twitter/areus/128.jpg"},{"id":35,"firstName":"Carolina","surName":"Parker","address":"803 Dickens Cliff","avatar":"https://s3.amazonaws.com/uifaces/faces/twitter/fabbianz/128.jpg"},{"id":36,"firstName":"Clifton","surName":"King","address":"1207 Gulgowski Cove","avatar":"https://s3.amazonaws.com/uifaces/faces/twitter/AlbertoCococi/128.jpg"},{"id":37,"firstName":"Rowan","surName":"Sanford","address":"33166 Greyson Pine","avatar":"https://s3.amazonaws.com/uifaces/faces/twitter/sur4dye/128.jpg"},{"id":38,"firstName":"Benjamin","surName":"Pouros","address":"19584 Koch Vista","avatar":"https://s3.amazonaws.com/uifaces/faces/twitter/dansowter/128.jpg"},{"id":39,"firstName":"Damian","surName":"Torphy","address":"9809 Johnnie Lodge","avatar":"https://s3.amazonaws.com/uifaces/faces/twitter/rtyukmaev/128.jpg"},{"id":40,"firstName":"Elenor","surName":"Hahn","address":"194 Schmeler Forge","avatar":"https://s3.amazonaws.com/uifaces/faces/twitter/stushona/128.jpg"},{"id":41,"firstName":"Eda","surName":"D'Amore","address":"8672 Klocko Stream","avatar":"https://s3.amazonaws.com/uifaces/faces/twitter/silvanmuhlemann/128.jpg"},{"id":42,"firstName":"Zola","surName":"Gaylord","address":"3005 Albertha Trail","avatar":"https://s3.amazonaws.com/uifaces/faces/twitter/benjamin_knight/128.jpg"},{"id":43,"firstName":"Shanie","surName":"Nolan","address":"445 Eichmann Keys","avatar":"https://s3.amazonaws.com/uifaces/faces/twitter/a_brixen/128.jpg"},{"id":44,"firstName":"Ocie","surName":"Botsford","address":"25423 Lavern Flat","avatar":"https://s3.amazonaws.com/uifaces/faces/twitter/myastro/128.jpg"},{"id":45,"firstName":"Archibald","surName":"Hudson","address":"7122 O'Hara Skyway","avatar":"https://s3.amazonaws.com/uifaces/faces/twitter/gcmorley/128.jpg"},{"id":46,"firstName":"Thea","surName":"King","address":"95762 Viola Mountain","avatar":"https://s3.amazonaws.com/uifaces/faces/twitter/hfalucas/128.jpg"},{"id":47,"firstName":"Martina","surName":"Skiles","address":"998 Jody Course","avatar":"https://s3.amazonaws.com/uifaces/faces/twitter/gregkilian/128.jpg"},{"id":48,"firstName":"Karolann","surName":"Mraz","address":"392 Cummings Center","avatar":"https://s3.amazonaws.com/uifaces/faces/twitter/chrisslowik/128.jpg"},{"id":49,"firstName":"Theodora","surName":"Schaefer","address":"61286 Murphy Inlet","avatar":"https://s3.amazonaws.com/uifaces/faces/twitter/kurafire/128.jpg"},{"id":50,"firstName":"Linnea","surName":"Roberts","address":"1352 Harber Gardens","avatar":"https://s3.amazonaws.com/uifaces/faces/twitter/meelford/128.jpg"}],"accounts":[{"id":1,"email":"admin@admin.com","userName":"admin","passWord":"admin"},{"id":2,"email":"Connor_Abbott74@yahoo.com","userName":"Eloise.Senger","passWord":"8KpGmcOR1kc8jbn"},{"id":3,"email":"Mya63@gmail.com","userName":"Nicolas_Daugherty36","passWord":"CWq4J4YY0baULEx"},{"id":4,"email":"Aryanna_Runolfsdottir53@yahoo.com","userName":"Vernie13","passWord":"ifI1zM_2yxrwKaY"},{"id":5,"email":"Fanny_Johnston72@yahoo.com","userName":"Geo97","passWord":"FJQ5xk3pC3eRnQG"},{"id":6,"email":"Berry_Runte13@yahoo.com","userName":"Houston_Yundt","passWord":"VnklqVnBNovS_TT"},{"id":7,"email":"Breanna.Dach@yahoo.com","userName":"Emely49","passWord":"WdajTFXOVF1A7Oz"},{"id":8,"email":"Eduardo.Walter@gmail.com","userName":"Benedict.Greenfelder","passWord":"1lJByJ72wiGeIBv"},{"id":9,"email":"Margarete_Marks37@gmail.com","userName":"Emile_OKeefe","passWord":"FUfLAoogn1VqG9R"},{"id":10,"email":"Joshua.Spinka98@hotmail.com","userName":"Frieda.Schumm","passWord":"1PzEh2w5QaSLvWc"},{"id":11,"email":"Danyka3@hotmail.com","userName":"Elisabeth.Hermiston46","passWord":"auQ6ZhqnC1KtwPA"},{"id":12,"email":"Roger.Lehner50@hotmail.com","userName":"Kaylee_Herzog29","passWord":"maDAa6_S6RLU1UE"},{"id":13,"email":"Brycen.Morissette@hotmail.com","userName":"Audie_Bogan","passWord":"eZQ8sBUSeOj5ADW"},{"id":14,"email":"Robin71@gmail.com","userName":"Gerard.Parker63","passWord":"4XNJ75DPpxgt0rh"},{"id":15,"email":"Lenora35@gmail.com","userName":"Cordia.Harris94","passWord":"XbSt5XwV3sF7tD9"},{"id":16,"email":"Darien81@gmail.com","userName":"Immanuel95","passWord":"rp8fzV50KikLWWA"},{"id":17,"email":"Libbie86@yahoo.com","userName":"Logan.Block","passWord":"JpTdRpQV8aOj2Wl"},{"id":18,"email":"Garnett21@gmail.com","userName":"Summer.Blick11","passWord":"CV07Phin2Eo6dO0"},{"id":19,"email":"Emily.Stokes@gmail.com","userName":"Gwen.Rolfson10","passWord":"Z7ub3HeqEmb6rpU"},{"id":20,"email":"Regan73@gmail.com","userName":"Priscilla_Jerde56","passWord":"4J6Kpg1L9vbiQMQ"},{"id":21,"email":"Hilbert_Stroman68@yahoo.com","userName":"Maybell_Greenholt93","passWord":"drVo7GlxDwastIX"},{"id":22,"email":"Buster.Jast54@hotmail.com","userName":"Mozell43","passWord":"Rwzd0036l1Fed3y"},{"id":23,"email":"Gunner_Wintheiser@hotmail.com","userName":"Isaias39","passWord":"JJVItcBfEhJgoGF"},{"id":24,"email":"Vivianne_Klein@hotmail.com","userName":"Simone.Ernser","passWord":"Oog2Xdw56tODbVU"},{"id":25,"email":"Patrick.Stanton@gmail.com","userName":"Madeline57","passWord":"nmPEEbg2LpJt9Dw"},{"id":26,"email":"Ressie98@gmail.com","userName":"Leopoldo85","passWord":"5olVNpoPKsh5xWj"},{"id":27,"email":"Janie.Rice@yahoo.com","userName":"Jesus_Yundt","passWord":"a7B9HSd8HCKR86Q"},{"id":28,"email":"Janick61@yahoo.com","userName":"Russell47","passWord":"yILcP9ZkmTbTw8H"},{"id":29,"email":"Nasir_Larson@gmail.com","userName":"Clay.Feeney","passWord":"cPzstaafojiOpx5"},{"id":30,"email":"Maria61@gmail.com","userName":"Davin21","passWord":"1wAvNrPQfK3c_BD"},{"id":31,"email":"Reinhold.Ratke@hotmail.com","userName":"Prudence_Blanda","passWord":"XYXCS8vyEQesuvC"},{"id":32,"email":"Jamie.Skiles@gmail.com","userName":"Elvera70","passWord":"7cYilehaKfmxwX1"},{"id":33,"email":"Frankie.Kertzmann@yahoo.com","userName":"Hans_Schaefer26","passWord":"eJezvtupocLOvC1"},{"id":34,"email":"Beryl43@gmail.com","userName":"Aiden.Wiza","passWord":"eByrqeClEiWD0p2"},{"id":35,"email":"Katharina_Haag69@yahoo.com","userName":"Lola.Funk13","passWord":"9XXxs0zrmFJ5q0P"},{"id":36,"email":"Annabel54@gmail.com","userName":"Derek_Hand","passWord":"h_p05Vz_T_kzzKe"},{"id":37,"email":"Lorenz28@gmail.com","userName":"Ettie50","passWord":"j_OuWHWbplLw4Sy"},{"id":38,"email":"Jaycee.Pfeffer54@yahoo.com","userName":"Okey_Stroman86","passWord":"t9BqKoBtAmFvMad"},{"id":39,"email":"Phyllis53@gmail.com","userName":"Deangelo.Weimann","passWord":"euPHFyarHrmpbMK"},{"id":40,"email":"Reina92@yahoo.com","userName":"Alfreda59","passWord":"31DtPzkSV9LmcbT"},{"id":41,"email":"Gwendolyn.Parisian@yahoo.com","userName":"Lemuel_Gulgowski1","passWord":"8LwJr6yz1E46SwM"},{"id":42,"email":"Eldon_Volkman@hotmail.com","userName":"Arjun25","passWord":"rWJKISc0joMmMrp"},{"id":43,"email":"Lucio81@hotmail.com","userName":"Trenton33","passWord":"aZO8AzVW7GJGZkn"},{"id":44,"email":"Sebastian_Terry@hotmail.com","userName":"Brown.Berge7","passWord":"m_c8Kg5X1DQahYU"},{"id":45,"email":"Haleigh_Bradtke@yahoo.com","userName":"Leonard.Lakin","passWord":"ffvN94dqY7l000q"},{"id":46,"email":"Sheridan_Padberg76@hotmail.com","userName":"Vladimir_Bergnaum","passWord":"ImRyY7VQfa8rQyb"},{"id":47,"email":"Estevan_Homenick@gmail.com","userName":"Verlie67","passWord":"pwq2fuWOnVOrpo8"},{"id":48,"email":"Jules.Kunde@gmail.com","userName":"Hayley.Kohler","passWord":"YAIowFXYPzRzoLt"},{"id":49,"email":"Kacey_McCullough37@gmail.com","userName":"Felipe73","passWord":"c0zbaqBQbUweTd_"},{"id":50,"email":"Adriel82@gmail.com","userName":"Monte_Williamson","passWord":"uQuWp4RPAJyqrge"}]}